{
  "success": true,
  "data": {
    "topicList": [
      {
        "id": 1,
        "title": "故事",
        "imgUrl": "http://upload.jianshu.io/collections/images/95/1.jpg?imageMogr2/auto-orient/strip|imageView2/1/w/64/h/64"
      },
      {
        "id": 2,
        "title": "摄影",
        "imgUrl": "//upload.jianshu.io/collections/images/83/1.jpg?imageMogr2/auto-orient/strip|imageView2/1/w/64/h/64"
      }
    ],
    "articleList": [
      {
        "id": 1,
        "title": "家里断网好无聊，正好最近学了Python来破解下邻居的WiFi试试！",
        "desc": "家里WiFi没网了，贼无聊，正好隔壁几家的邻居都出去玩了，偷偷的破解他们的WiFi用用应该不要紧的~ Python是我刚学的，破解WiFi也是临...",
        "imgUrl": "//upload-images.jianshu.io/upload_images/12778909-c8c11ffc75ecf0d2?imageMogr2/auto-orient/strip|imageView2/1/w/300/h/240"
      },
      {
        "id": 2,
        "title": "一个中学教师的忠告:别把你的女儿打扮得太漂亮！",
        "desc": "每天上学前，给女儿梳个漂亮的发型，带几个好看的发卡，再穿上美丽的公主裙。。。 看着被你打扮得花儿一样的小美女，你打心眼里自豪。“俺家妞儿长的就是...",
        "imgUrl": "//upload-images.jianshu.io/upload_images/13530470-778baa071c046b64.jpg?imageMogr2/auto-orient/strip|imageView2/1/w/300/h/240"
      },
      {
        "id": 3,
        "title": "家里断网好无聊，正好最近学了Python来破解下邻居的WiFi试试！",
        "desc": "家里WiFi没网了，贼无聊，正好隔壁几家的邻居都出去玩了，偷偷的破解他们的WiFi用用应该不要紧的~ Python是我刚学的，破解WiFi也是临...",
        "imgUrl": "//upload-images.jianshu.io/upload_images/12778909-c8c11ffc75ecf0d2?imageMogr2/auto-orient/strip|imageView2/1/w/300/h/240"
      },
      {
        "id": 4,
        "title": "一个中学教师的忠告:别把你的女儿打扮得太漂亮！",
        "desc": "每天上学前，给女儿梳个漂亮的发型，带几个好看的发卡，再穿上美丽的公主裙。。。 看着被你打扮得花儿一样的小美女，你打心眼里自豪。“俺家妞儿长的就是...",
        "imgUrl": "//upload-images.jianshu.io/upload_images/13530470-778baa071c046b64.jpg?imageMogr2/auto-orient/strip|imageView2/1/w/300/h/240"
      }
    ],
    "recommendList": [
      {
        "id": 1,
        "imgUrl": "http://cdn2.jianshu.io/assets/web/banner-s-3-7123fd94750759acf7eca05b871e9d17.png"
      },
      {
        "id": 2,
        "imgUrl": "http://cdn2.jianshu.io/assets/web/banner-s-4-b70da70d679593510ac93a172dfbaeaa.png"
      },
      {
        "id": 3,
        "imgUrl": "http://cdn2.jianshu.io/assets/web/banner-s-7-1a0222c91694a1f38e610be4bf9669be.png"
      },
      {
        "id": 4,
        "imgUrl": "http://cdn2.jianshu.io/assets/web/banner-s-5-4ba25cf5041931a0ed2062828b4064cb.png"
      },
      {
        "id": 5,
        "imgUrl": "http://cdn2.jianshu.io/assets/web/banner-s-6-c4d6335bfd688f2ca1115b42b04c28a7.png"
      }
    ]
  }
}